tigrbl_kms/__init__.py
tigrbl_kms/__main__.py
tigrbl_kms/app.py
tigrbl_kms/cli.py
tigrbl_kms/orm/__init__.py
tigrbl_kms/orm/key.py
tigrbl_kms/orm/key_version.py
tigrbl_kms/utils.py
tigrbl_kms-0.3.0.dev5.dist-info/LICENSE
tigrbl_kms-0.3.0.dev5.dist-info/METADATA
tigrbl_kms-0.3.0.dev5.dist-info/WHEEL
tigrbl_kms-0.3.0.dev5.dist-info/entry_points.txt
tigrbl_kms-0.3.0.dev5.dist-info/RECORD
