Metadata-Version: 2.3
Name: tigrbl-kms
Version: 0.3.0.dev5
Summary: A Tigrbl key management service for Swarmauri.
License: Apache-2.0
Author: Swarmauri Team
Author-email: team@swarmauri.com
Requires-Python: >=3.10,<3.13
Classifier: License :: OSI Approved :: Apache Software License
Classifier: Development Status :: 3 - Alpha
Classifier: Programming Language :: Python :: 3.10
Classifier: Programming Language :: Python :: 3.11
Classifier: Programming Language :: Python :: 3.12
Requires-Dist: asyncpg (>=0.29,<1.0)
Requires-Dist: fastapi (>=0.100.0)
Requires-Dist: pydantic (>=2.0.0)
Requires-Dist: sqlalchemy[asyncio] (>=2.0.0)
Requires-Dist: swarmauri_base
Requires-Dist: swarmauri_core
Requires-Dist: swarmauri_crypto_paramiko
Requires-Dist: swarmauri_standard
Requires-Dist: tigrbl
Requires-Dist: typer (>=0.12.3)
Requires-Dist: uvicorn[standard] (>=0.29)
